setup.py
KessMatrix/LinearAlg.py
KessMatrix/___init__.py
KessMatrix/test.py
KessMatrix.egg-info/PKG-INFO
KessMatrix.egg-info/SOURCES.txt
KessMatrix.egg-info/dependency_links.txt
KessMatrix.egg-info/not-zip-safe
KessMatrix.egg-info/top_level.txt