Metadata-Version: 2.1
Name: KessMatrix
Version: 1.0
Summary: Linear Algebra package
Author: Joshua Kessler
Author-email: jbarlowk@gmail.com
